dimsim/__init__.py
dimsim/core/__init__.py
dimsim/core/model.py
dimsim/data/.DS_Store
dimsim/data/__init__.py
dimsim/data/__init__.pyc
dimsim/data/pinyin_to_simplified.pickle
dimsim/data/pinyin_to_traditional.pickle
dimsim/utils/__init__.py
dimsim/utils/maps.py
dimsim/utils/pinyin.py
dimsim/utils/utils.py
dimsim-0.2.2.dist-info/LICENSE
dimsim-0.2.2.dist-info/METADATA
dimsim-0.2.2.dist-info/WHEEL
dimsim-0.2.2.dist-info/top_level.txt
dimsim-0.2.2.dist-info/RECORD
